{"title":"读你的眼睛","date":"","imageries":{"眼睛":[{"part":"n","lineNum":"1","lineIndex":"3","imageryIndex":"0"},{"part":"n","lineNum":"16","lineIndex":"3","imageryIndex":"0"}],"一封封":[{"part":"ns","lineNum":"2","lineIndex":"2","imageryIndex":"0"}],"信笺":[{"part":"n","lineNum":"2","lineIndex":"10","imageryIndex":"1"}],"海":[{"part":"n","lineNum":"3","lineIndex":"2","imageryIndex":"0"},{"part":"n","lineNum":"5","lineIndex":"2","imageryIndex":"0"}],"字":[{"part":"n","lineNum":"4","lineIndex":"3","imageryIndex":"0"},{"part":"n","lineNum":"4","lineIndex":"5","imageryIndex":"1"}],"碎片":[{"part":"n","lineNum":"4","lineIndex":"7","imageryIndex":"2"}],"日光":[{"part":"n","lineNum":"4","lineIndex":"11","imageryIndex":"3"}],"鳞光":[{"part":"n","lineNum":"5","lineIndex":"4","imageryIndex":"1"}],"心语":[{"part":"n","lineNum":"6","lineIndex":"2","imageryIndex":"0"}],"唇":[{"part":"n","lineNum":"8","lineIndex":"3","imageryIndex":"0"}],"疆土":[{"part":"n","lineNum":"10","lineIndex":"0","imageryIndex":"0"}],"我搏":[{"part":"n","lineNum":"11","lineIndex":"5","imageryIndex":"0"}],"频率":[{"part":"n","lineNum":"11","lineIndex":"8","imageryIndex":"1"}],"语言":[{"part":"n","lineNum":"12","lineIndex":"5","imageryIndex":"0"}],"沙":[{"part":"n","lineNum":"13","lineIndex":"3","imageryIndex":"0"}],"粒粒":[{"part":"n","lineNum":"14","lineIndex":"2","imageryIndex":"0"}],"话语":[{"part":"n","lineNum":"17","lineIndex":"6","imageryIndex":"0"}],"海洋":[{"part":"ns","lineNum":"17","lineIndex":"9","imageryIndex":"1"}]}}
{"title":"筑路","date":"","imageries":{"计划":[{"part":"n","lineNum":"1","lineIndex":"4","imageryIndex":"0"}],"图":[{"part":"n","lineNum":"1","lineIndex":"6","imageryIndex":"1"}],"诗句":[{"part":"n","lineNum":"1","lineIndex":"9","imageryIndex":"2"},{"part":"n","lineNum":"20","lineIndex":"3","imageryIndex":"1"}],"赋体":[{"part":"n","lineNum":"5","lineIndex":"3","imageryIndex":"0"}],"意象":[{"part":"n","lineNum":"9","lineIndex":"5","imageryIndex":"0"}],"遗漏":[{"part":"n","lineNum":"10","lineIndex":"2","imageryIndex":"0"}],"隐喻":[{"part":"n","lineNum":"10","lineIndex":"6","imageryIndex":"1"}],"路灯":[{"part":"n","lineNum":"12","lineIndex":"2","imageryIndex":"0"}],"思考性":[{"part":"n","lineNum":"14","lineIndex":"2","imageryIndex":"0"}],"地下水":[{"part":"n","lineNum":"15","lineIndex":"0","imageryIndex":"0"}],"电缆":[{"part":"n","lineNum":"16","lineIndex":"2","imageryIndex":"0"}],"飞跃性":[{"part":"n","lineNum":"16","lineIndex":"5","imageryIndex":"1"}],"路":[{"part":"n","lineNum":"19","lineIndex":"0","imageryIndex":"0"}],"漫长":[{"part":"n","lineNum":"20","lineIndex":"0","imageryIndex":"0"}]}}
{"title":"伐木","date":"","imageries":{"黑夜":[{"part":"n","lineNum":"1","lineIndex":"0","imageryIndex":"0"}],"卷席":[{"part":"n","lineNum":"1","lineIndex":"2","imageryIndex":"1"}],"时刻":[{"part":"n","lineNum":"1","lineIndex":"5","imageryIndex":"2"}],"屏息":[{"part":"n","lineNum":"3","lineIndex":"0","imageryIndex":"0"}],"雾":[{"part":"n","lineNum":"4","lineIndex":"0","imageryIndex":"0"}],"碎声":[{"part":"n","lineNum":"5","lineIndex":"3","imageryIndex":"0"}],"伐木者":[{"part":"n","lineNum":"7","lineIndex":"0","imageryIndex":"0"}],"锯齿":[{"part":"n","lineNum":"7","lineIndex":"4","imageryIndex":"1"}],"芒鞋":[{"part":"n","lineNum":"7","lineIndex":"6","imageryIndex":"2"}],"切腹":[{"part":"n","lineNum":"8","lineIndex":"2","imageryIndex":"0"}],"姿态":[{"part":"n","lineNum":"8","lineIndex":"7","imageryIndex":"1"}],"众树":[{"part":"n","lineNum":"9","lineIndex":"0","imageryIndex":"0"}],"羽毛":[{"part":"n","lineNum":"10","lineIndex":"6","imageryIndex":"0"}],"燎原":[{"part":"n","lineNum":"11","lineIndex":"2","imageryIndex":"0"}],"腐臭":[{"part":"n","lineNum":"13","lineIndex":"0","imageryIndex":"0"}],"焦味":[{"part":"n","lineNum":"13","lineIndex":"3","imageryIndex":"1"}],"灰烬":[{"part":"n","lineNum":"14","lineIndex":"4","imageryIndex":"0"}],"太阳":[{"part":"ns","lineNum":"16","lineIndex":"0","imageryIndex":"0"}],"面孔":[{"part":"n","lineNum":"17","lineIndex":"5","imageryIndex":"0"}],"嘴盆":[{"part":"n","lineNum":"18","lineIndex":"3","imageryIndex":"0"}],"火舌":[{"part":"n","lineNum":"19","lineIndex":"6","imageryIndex":"0"}],"食尸":[{"part":"n","lineNum":"21","lineIndex":"0","imageryIndex":"0"}],"鸟":[{"part":"n","lineNum":"21","lineIndex":"2","imageryIndex":"1"}],"振翼":[{"part":"n","lineNum":"21","lineIndex":"10","imageryIndex":"2"}],"温床":[{"part":"n","lineNum":"22","lineIndex":"0","imageryIndex":"0"},{"part":"n","lineNum":"23","lineIndex":"0","imageryIndex":"0"}],"天空":[{"part":"n","lineNum":"24","lineIndex":"0","imageryIndex":"0"}]}}
{"title":"海岸极限","date":"","imageries":{"甘美":[{"part":"ns","lineNum":"2","lineIndex":"0","imageryIndex":"0"}],"夜":[{"part":"n","lineNum":"2","lineIndex":"3","imageryIndex":"1"}],"风":[{"part":"n","lineNum":"5","lineIndex":"1","imageryIndex":"0"}],"人":[{"part":"n","lineNum":"10","lineIndex":"2","imageryIndex":"0"}],"海":[{"part":"n","lineNum":"12","lineIndex":"0","imageryIndex":"0"},{"part":"n","lineNum":"41","lineIndex":"3","imageryIndex":"0"}],"浪涛":[{"part":"n","lineNum":"17","lineIndex":"0","imageryIndex":"0"}],"脚印":[{"part":"n","lineNum":"21","lineIndex":"0","imageryIndex":"0"},{"part":"n","lineNum":"25","lineIndex":"0","imageryIndex":"0"}],"水":[{"part":"n","lineNum":"29","lineIndex":"5","imageryIndex":"0"},{"part":"n","lineNum":"30","lineIndex":"3","imageryIndex":"0"}],"深渊":[{"part":"ns","lineNum":"31","lineIndex":"2","imageryIndex":"0"}],"岸":[{"part":"n","lineNum":"42","lineIndex":"3","imageryIndex":"0"}]}}
{"title":"祝福的小红花","date":"","imageries":{"女儿":[{"part":"n","lineNum":"1","lineIndex":"7","imageryIndex":"0"},{"part":"n","lineNum":"3","lineIndex":"12","imageryIndex":"2"}],"母亲":[{"part":"n","lineNum":"2","lineIndex":"2","imageryIndex":"0"},{"part":"n","lineNum":"3","lineIndex":"0","imageryIndex":"0"},{"part":"n","lineNum":"10","lineIndex":"0","imageryIndex":"0"},{"part":"n","lineNum":"22","lineIndex":"0","imageryIndex":"0"}],"坟":[{"part":"n","lineNum":"2","lineIndex":"5","imageryIndex":"1"}],"疼爱":[{"part":"n","lineNum":"3","lineIndex":"6","imageryIndex":"1"}],"公墓":[{"part":"n","lineNum":"4","lineIndex":"5","imageryIndex":"0"}],"坟地":[{"part":"n","lineNum":"5","lineIndex":"0","imageryIndex":"0"}],"凉风":[{"part":"n","lineNum":"6","lineIndex":"5","imageryIndex":"0"}],"手势":[{"part":"n","lineNum":"9","lineIndex":"3","imageryIndex":"0"}],"媳妇":[{"part":"n","lineNum":"13","lineIndex":"7","imageryIndex":"0"}],"冥纸":[{"part":"n","lineNum":"17","lineIndex":"0","imageryIndex":"0"}],"影子":[{"part":"n","lineNum":"18","lineIndex":"5","imageryIndex":"0"}],"墓碑":[{"part":"n","lineNum":"19","lineIndex":"3","imageryIndex":"0"}],"刻字":[{"part":"n","lineNum":"19","lineIndex":"6","imageryIndex":"1"}],"象":[{"part":"n","lineNum":"27","lineIndex":"0","imageryIndex":"0"}],"坟头":[{"part":"n","lineNum":"27","lineIndex":"1","imageryIndex":"1"}],"红色":[{"part":"n","lineNum":"27","lineIndex":"7","imageryIndex":"2"}],"小花":[{"part":"n","lineNum":"27","lineIndex":"9","imageryIndex":"3"}],"笑容":[{"part":"n","lineNum":"29","lineIndex":"3","imageryIndex":"0"}]}}
{"title":"狮子","date":"","imageries":{"大":[{"part":"n","lineNum":"1","lineIndex":"1","imageryIndex":"0"}],"草原":[{"part":"n","lineNum":"1","lineIndex":"2","imageryIndex":"1"}],"铁栏":[{"part":"n","lineNum":"1","lineIndex":"5","imageryIndex":"2"}],"石墙":[{"part":"n","lineNum":"2","lineIndex":"4","imageryIndex":"0"}],"故国":[{"part":"ns","lineNum":"3","lineIndex":"5","imageryIndex":"0"}],"家园":[{"part":"n","lineNum":"3","lineIndex":"8","imageryIndex":"1"}],"人间":[{"part":"n","lineNum":"5","lineIndex":"0","imageryIndex":"0"}],"游戏":[{"part":"n","lineNum":"6","lineIndex":"7","imageryIndex":"0"}],"舞台":[{"part":"n","lineNum":"8","lineIndex":"5","imageryIndex":"0"}],"悲剧":[{"part":"n","lineNum":"10","lineIndex":"2","imageryIndex":"0"}],"人潮":[{"part":"n","lineNum":"12","lineIndex":"2","imageryIndex":"0"},{"part":"n","lineNum":"13","lineIndex":"3","imageryIndex":"0"}],"人类":[{"part":"n","lineNum":"15","lineIndex":"0","imageryIndex":"0"}]}}
{"title":"星的位置","date":"","imageries":{"总想":[{"part":"n","lineNum":"1","lineIndex":"1","imageryIndex":"0"}],"宿命":[{"part":"n","lineNum":"2","lineIndex":"3","imageryIndex":"0"}],"天空":[{"part":"n","lineNum":"5","lineIndex":"6","imageryIndex":"0"}],"脸庞":[{"part":"n","lineNum":"6","lineIndex":"7","imageryIndex":"0"}],"陌生":[{"part":"n","lineNum":"8","lineIndex":"2","imageryIndex":"0"}],"眼光":[{"part":"n","lineNum":"8","lineIndex":"5","imageryIndex":"1"}],"流浪":[{"part":"n","lineNum":"11","lineIndex":"2","imageryIndex":"0"}],"路途":[{"part":"n","lineNum":"11","lineIndex":"5","imageryIndex":"1"}],"头颅":[{"part":"n","lineNum":"13","lineIndex":"7","imageryIndex":"0"}],"古井":[{"part":"n","lineNum":"14","lineIndex":"5","imageryIndex":"0"}],"水底":[{"part":"n","lineNum":"15","lineIndex":"12","imageryIndex":"0"}],"名字":[{"part":"n","lineNum":"17","lineIndex":"7","imageryIndex":"0"}]}}
{"title":"水牛","date":"","imageries":{"水牛":[{"part":"n","lineNum":"1","lineIndex":"0","imageryIndex":"0"},{"part":"n","lineNum":"4","lineIndex":"0","imageryIndex":"0"},{"part":"n","lineNum":"10","lineIndex":"2","imageryIndex":"0"},{"part":"n","lineNum":"14","lineIndex":"0","imageryIndex":"0"}],"颜色":[{"part":"n","lineNum":"1","lineIndex":"11","imageryIndex":"1"}],"天空":[{"part":"n","lineNum":"2","lineIndex":"4","imageryIndex":"0"},{"part":"n","lineNum":"5","lineIndex":"10","imageryIndex":"1"},{"part":"n","lineNum":"7","lineIndex":"0","imageryIndex":"0"},{"part":"n","lineNum":"8","lineIndex":"2","imageryIndex":"0"},{"part":"n","lineNum":"9","lineIndex":"0","imageryIndex":"0"},{"part":"n","lineNum":"12","lineIndex":"0","imageryIndex":"0"}],"蓝":[{"part":"n","lineNum":"2","lineIndex":"7","imageryIndex":"1"}],"角是":[{"part":"n","lineNum":"5","lineIndex":"6","imageryIndex":"0"}],"时刻":[{"part":"n","lineNum":"9","lineIndex":"10","imageryIndex":"1"}],"地平线":[{"part":"n","lineNum":"13","lineIndex":"1","imageryIndex":"0"}],"血":[{"part":"n","lineNum":"16","lineIndex":"12","imageryIndex":"0"}]}}
{"title":"日出日落","date":"","imageries":{"手汗":[{"part":"n","lineNum":"2","lineIndex":"0","imageryIndex":"0"}],"大地":[{"part":"n","lineNum":"2","lineIndex":"3","imageryIndex":"1"}],"湿润":[{"part":"n","lineNum":"2","lineIndex":"5","imageryIndex":"2"}],"土屋":[{"part":"n","lineNum":"3","lineIndex":"7","imageryIndex":"0"}],"角隅":[{"part":"n","lineNum":"3","lineIndex":"10","imageryIndex":"1"}],"云":[{"part":"n","lineNum":"4","lineIndex":"10","imageryIndex":"0"}],"太阳":[{"part":"ns","lineNum":"6","lineIndex":"0","imageryIndex":"0"}],"铜色":[{"part":"n","lineNum":"6","lineIndex":"3","imageryIndex":"1"}],"履带":[{"part":"n","lineNum":"6","lineIndex":"6","imageryIndex":"2"}],"皮肤":[{"part":"n","lineNum":"6","lineIndex":"13","imageryIndex":"3"}],"力":[{"part":"n","lineNum":"7","lineIndex":"0","imageryIndex":"0"}],"盐水":[{"part":"n","lineNum":"7","lineIndex":"2","imageryIndex":"1"}],"肌肉":[{"part":"n","lineNum":"7","lineIndex":"5","imageryIndex":"2"}],"滑流":[{"part":"n","lineNum":"7","lineIndex":"8","imageryIndex":"3"}],"风雨":[{"part":"n","lineNum":"8","lineIndex":"3","imageryIndex":"0"}],"汗滴":[{"part":"n","lineNum":"9","lineIndex":"4","imageryIndex":"0"}],"芳香":[{"part":"n","lineNum":"15","lineIndex":"6","imageryIndex":"0"}],"泥染":[{"part":"n","lineNum":"15","lineIndex":"8","imageryIndex":"1"}],"土地":[{"part":"n","lineNum":"15","lineIndex":"10","imageryIndex":"2"},{"part":"n","lineNum":"30","lineIndex":"12","imageryIndex":"0"}],"种子":[{"part":"n","lineNum":"16","lineIndex":"5","imageryIndex":"0"}],"宿愿":[{"part":"n","lineNum":"17","lineIndex":"5","imageryIndex":"0"}],"锄头":[{"part":"n","lineNum":"24","lineIndex":"0","imageryIndex":"0"}],"胼手":[{"part":"n","lineNum":"25","lineIndex":"4","imageryIndex":"0"}],"泥土":[{"part":"n","lineNum":"26","lineIndex":"0","imageryIndex":"0"}],"日落":[{"part":"n","lineNum":"29","lineIndex":"0","imageryIndex":"0"}],"芽":[{"part":"n","lineNum":"31","lineIndex":"0","imageryIndex":"0"}],"结":[{"part":"n","lineNum":"34","lineIndex":"1","imageryIndex":"0"}],"田亩":[{"part":"n","lineNum":"36","lineIndex":"0","imageryIndex":"0"}],"血汗":[{"part":"n","lineNum":"36","lineIndex":"5","imageryIndex":"1"}],"古道":[{"part":"n","lineNum":"37","lineIndex":"0","imageryIndex":"0"}],"脚印":[{"part":"n","lineNum":"37","lineIndex":"5","imageryIndex":"1"}],"日子":[{"part":"n","lineNum":"40","lineIndex":"5","imageryIndex":"0"}]}}
