{"title":"桑","date":"","imageries":{"母亲":[{"part":"n","lineNum":"2","lineIndex":"3","imageryIndex":"0"},{"part":"n","lineNum":"14","lineIndex":"0","imageryIndex":"0"}],"绸子":[{"part":"n","lineNum":"2","lineIndex":"7","imageryIndex":"1"}],"窗户":[{"part":"n","lineNum":"3","lineIndex":"4","imageryIndex":"0"}],"路径":[{"part":"n","lineNum":"4","lineIndex":"4","imageryIndex":"0"}],"远山":[{"part":"ns","lineNum":"5","lineIndex":"0","imageryIndex":"0"}],"秀色":[{"part":"n","lineNum":"5","lineIndex":"3","imageryIndex":"1"}],"雨":[{"part":"n","lineNum":"5","lineIndex":"7","imageryIndex":"2"}],"落地":[{"part":"n","lineNum":"7","lineIndex":"4","imageryIndex":"0"}],"镜子":[{"part":"n","lineNum":"9","lineIndex":"6","imageryIndex":"0"}],"声音":[{"part":"n","lineNum":"11","lineIndex":"0","imageryIndex":"0"}],"天气":[{"part":"n","lineNum":"12","lineIndex":"0","imageryIndex":"0"}],"衣衫":[{"part":"n","lineNum":"12","lineIndex":"5","imageryIndex":"1"}],"烛照":[{"part":"n","lineNum":"13","lineIndex":"2","imageryIndex":"0"}],"面容":[{"part":"n","lineNum":"14","lineIndex":"2","imageryIndex":"1"}]}}
{"title":"梅花","date":"","imageries":{"书卷":[{"part":"n","lineNum":"1","lineIndex":"0","imageryIndex":"0"}],"素手":[{"part":"n","lineNum":"1","lineIndex":"3","imageryIndex":"1"}],"屋子里":[{"part":"n","lineNum":"2","lineIndex":"0","imageryIndex":"0"}],"空":[{"part":"n","lineNum":"2","lineIndex":"3","imageryIndex":"1"}],"花瓶":[{"part":"n","lineNum":"2","lineIndex":"5","imageryIndex":"2"}],"等候":[{"part":"n","lineNum":"2","lineIndex":"7","imageryIndex":"3"}],"雪色":[{"part":"n","lineNum":"3","lineIndex":"2","imageryIndex":"0"}],"容貌":[{"part":"n","lineNum":"4","lineIndex":"0","imageryIndex":"0"}],"木器":[{"part":"n","lineNum":"4","lineIndex":"3","imageryIndex":"1"}],"一团和气":[{"part":"n","lineNum":"4","lineIndex":"5","imageryIndex":"2"}],"衣衫":[{"part":"n","lineNum":"5","lineIndex":"0","imageryIndex":"0"}],"石头":[{"part":"n","lineNum":"6","lineIndex":"2","imageryIndex":"0"}],"青黑":[{"part":"ns","lineNum":"6","lineIndex":"4","imageryIndex":"1"}],"清平":[{"part":"n","lineNum":"7","lineIndex":"10","imageryIndex":"0"}],"影子":[{"part":"n","lineNum":"8","lineIndex":"3","imageryIndex":"0"}],"天气":[{"part":"n","lineNum":"9","lineIndex":"3","imageryIndex":"0"}],"正值":[{"part":"n","lineNum":"9","lineIndex":"5","imageryIndex":"1"}],"日子":[{"part":"n","lineNum":"10","lineIndex":"0","imageryIndex":"0"}],"玉":[{"part":"n","lineNum":"10","lineIndex":"8","imageryIndex":"1"}],"酒":[{"part":"n","lineNum":"10","lineIndex":"12","imageryIndex":"2"}],"窗户":[{"part":"n","lineNum":"12","lineIndex":"2","imageryIndex":"0"}],"绸子":[{"part":"n","lineNum":"12","lineIndex":"5","imageryIndex":"1"}],"表面":[{"part":"n","lineNum":"12","lineIndex":"7","imageryIndex":"2"}],"日益":[{"part":"n","lineNum":"12","lineIndex":"9","imageryIndex":"3"}],"人":[{"part":"n","lineNum":"13","lineIndex":"3","imageryIndex":"0"}],"蜡火":[{"part":"n","lineNum":"14","lineIndex":"3","imageryIndex":"0"}],"滋润":[{"part":"n","lineNum":"15","lineIndex":"2","imageryIndex":"0"}],"肺腑":[{"part":"n","lineNum":"15","lineIndex":"4","imageryIndex":"1"}],"花色":[{"part":"n","lineNum":"16","lineIndex":"0","imageryIndex":"0"}],"皮肤":[{"part":"n","lineNum":"16","lineIndex":"4","imageryIndex":"1"}],"寒气":[{"part":"n","lineNum":"18","lineIndex":"3","imageryIndex":"0"}],"书":[{"part":"n","lineNum":"18","lineIndex":"6","imageryIndex":"1"}],"开花":[{"part":"n","lineNum":"19","lineIndex":"0","imageryIndex":"0"}],"陶瓷":[{"part":"n","lineNum":"20","lineIndex":"5","imageryIndex":"0"}],"中堂":[{"part":"ns","lineNum":"21","lineIndex":"0","imageryIndex":"0"}],"山水":[{"part":"ns","lineNum":"21","lineIndex":"2","imageryIndex":"1"}],"折花":[{"part":"n","lineNum":"22","lineIndex":"0","imageryIndex":"0"}],"手":[{"part":"n","lineNum":"22","lineIndex":"3","imageryIndex":"1"}]}}
{"title":"刀","date":"","imageries":{"刀":[{"part":"n","lineNum":"1","lineIndex":"8","imageryIndex":"0"},{"part":"n","lineNum":"26","lineIndex":"0","imageryIndex":"0"}],"皮下":[{"part":"n","lineNum":"1","lineIndex":"11","imageryIndex":"1"}],"插花":[{"part":"n","lineNum":"2","lineIndex":"1","imageryIndex":"0"}],"水":[{"part":"n","lineNum":"3","lineIndex":"3","imageryIndex":"0"},{"part":"n","lineNum":"16","lineIndex":"4","imageryIndex":"1"}],"闺房":[{"part":"n","lineNum":"4","lineIndex":"1","imageryIndex":"0"}],"妻子":[{"part":"n","lineNum":"4","lineIndex":"4","imageryIndex":"1"}],"窗门":[{"part":"n","lineNum":"5","lineIndex":"0","imageryIndex":"0"}],"流汗":[{"part":"n","lineNum":"6","lineIndex":"2","imageryIndex":"0"}],"手势":[{"part":"n","lineNum":"6","lineIndex":"10","imageryIndex":"1"}],"杀人":[{"part":"n","lineNum":"7","lineIndex":"0","imageryIndex":"0"}],"方向":[{"part":"n","lineNum":"7","lineIndex":"3","imageryIndex":"1"}],"金木":[{"part":"n","lineNum":"7","lineIndex":"8","imageryIndex":"2"}],"宫":[{"part":"n","lineNum":"8","lineIndex":"2","imageryIndex":"0"}],"人":[{"part":"n","lineNum":"8","lineIndex":"6","imageryIndex":"1"},{"part":"n","lineNum":"18","lineIndex":"11","imageryIndex":"2"},{"part":"n","lineNum":"27","lineIndex":"5","imageryIndex":"1"}],"椅子":[{"part":"n","lineNum":"9","lineIndex":"6","imageryIndex":"0"}],"空屋":[{"part":"n","lineNum":"11","lineIndex":"4","imageryIndex":"0"},{"part":"n","lineNum":"18","lineIndex":"3","imageryIndex":"0"}],"头颅":[{"part":"n","lineNum":"12","lineIndex":"0","imageryIndex":"0"}],"花朵":[{"part":"n","lineNum":"13","lineIndex":"4","imageryIndex":"0"}],"衣衫":[{"part":"n","lineNum":"14","lineIndex":"2","imageryIndex":"0"}],"肤色":[{"part":"n","lineNum":"14","lineIndex":"5","imageryIndex":"1"}],"想象":[{"part":"n","lineNum":"15","lineIndex":"6","imageryIndex":"0"}],"经历":[{"part":"n","lineNum":"16","lineIndex":"2","imageryIndex":"0"}],"水声":[{"part":"n","lineNum":"18","lineIndex":"8","imageryIndex":"1"}],"陆陆续续":[{"part":"n","lineNum":"19","lineIndex":"0","imageryIndex":"0"}],"花气":[{"part":"n","lineNum":"20","lineIndex":"0","imageryIndex":"0"}],"肺叶":[{"part":"n","lineNum":"20","lineIndex":"5","imageryIndex":"1"}],"持刀":[{"part":"n","lineNum":"20","lineIndex":"10","imageryIndex":"2"}],"眼睛":[{"part":"n","lineNum":"21","lineIndex":"0","imageryIndex":"0"}],"空气":[{"part":"n","lineNum":"21","lineIndex":"3","imageryIndex":"1"}],"引经据典":[{"part":"n","lineNum":"22","lineIndex":"2","imageryIndex":"0"}],"一带":[{"part":"n","lineNum":"23","lineIndex":"1","imageryIndex":"0"}],"绸子":[{"part":"n","lineNum":"23","lineIndex":"3","imageryIndex":"1"}],"祸乱":[{"part":"n","lineNum":"23","lineIndex":"7","imageryIndex":"2"}],"世道":[{"part":"n","lineNum":"25","lineIndex":"4","imageryIndex":"0"}],"清平":[{"part":"n","lineNum":"25","lineIndex":"6","imageryIndex":"1"}],"妻":[{"part":"n","lineNum":"26","lineIndex":"6","imageryIndex":"1"}],"风":[{"part":"n","lineNum":"26","lineIndex":"10","imageryIndex":"2"}],"花色":[{"part":"n","lineNum":"27","lineIndex":"2","imageryIndex":"0"}],"君临":[{"part":"ns","lineNum":"27","lineIndex":"8","imageryIndex":"2"}]}}
{"title":"听冬","date":"","imageries":{"落雪":[{"part":"n","lineNum":"2","lineIndex":"1","imageryIndex":"0"}],"疏影":[{"part":"n","lineNum":"2","lineIndex":"6","imageryIndex":"1"}],"月亮":[{"part":"n","lineNum":"2","lineIndex":"12","imageryIndex":"2"}],"枯苇":[{"part":"n","lineNum":"3","lineIndex":"2","imageryIndex":"0"}],"歌":[{"part":"n","lineNum":"3","lineIndex":"7","imageryIndex":"1"}],"逝者":[{"part":"n","lineNum":"4","lineIndex":"1","imageryIndex":"0"}],"水":[{"part":"n","lineNum":"7","lineIndex":"7","imageryIndex":"0"}],"舟":[{"part":"ns","lineNum":"7","lineIndex":"9","imageryIndex":"1"}],"空弦":[{"part":"n","lineNum":"8","lineIndex":"3","imageryIndex":"0"}],"源头":[{"part":"n","lineNum":"8","lineIndex":"13","imageryIndex":"1"}],"血痕":[{"part":"n","lineNum":"11","lineIndex":"1","imageryIndex":"0"}],"高山":[{"part":"ns","lineNum":"11","lineIndex":"4","imageryIndex":"1"}],"泪滴":[{"part":"n","lineNum":"11","lineIndex":"10","imageryIndex":"2"}],"清酒":[{"part":"n","lineNum":"11","lineIndex":"12","imageryIndex":"3"}],"铭骨":[{"part":"n","lineNum":"12","lineIndex":"9","imageryIndex":"0"}],"文":[{"part":"n","lineNum":"12","lineIndex":"12","imageryIndex":"1"}],"云":[{"part":"n","lineNum":"14","lineIndex":"3","imageryIndex":"0"}],"时候":[{"part":"n","lineNum":"14","lineIndex":"6","imageryIndex":"1"},{"part":"n","lineNum":"15","lineIndex":"6","imageryIndex":"1"}],"雨":[{"part":"n","lineNum":"15","lineIndex":"1","imageryIndex":"0"}],"踏雪":[{"part":"n","lineNum":"17","lineIndex":"5","imageryIndex":"0"}],"日子":[{"part":"n","lineNum":"18","lineIndex":"3","imageryIndex":"0"}],"归者":[{"part":"n","lineNum":"20","lineIndex":"4","imageryIndex":"0"}],"结庐":[{"part":"n","lineNum":"22","lineIndex":"7","imageryIndex":"0"}],"荒草":[{"part":"n","lineNum":"23","lineIndex":"10","imageryIndex":"0"}]}}
{"title":"炼气士","date":"","imageries":{"身形":[{"part":"n","lineNum":"1","lineIndex":"0","imageryIndex":"0"}],"水势":[{"part":"n","lineNum":"1","lineIndex":"4","imageryIndex":"1"}],"云气":[{"part":"n","lineNum":"2","lineIndex":"5","imageryIndex":"0"}],"衣袍":[{"part":"n","lineNum":"4","lineIndex":"3","imageryIndex":"0"}],"日见":[{"part":"n","lineNum":"4","lineIndex":"5","imageryIndex":"1"}],"月亮":[{"part":"n","lineNum":"7","lineIndex":"0","imageryIndex":"0"}],"气息":[{"part":"n","lineNum":"7","lineIndex":"3","imageryIndex":"1"}],"鼎中":[{"part":"ns","lineNum":"7","lineIndex":"7","imageryIndex":"2"}],"处":[{"part":"n","lineNum":"8","lineIndex":"4","imageryIndex":"0"}],"天空":[{"part":"n","lineNum":"9","lineIndex":"0","imageryIndex":"0"}],"山海":[{"part":"ns","lineNum":"10","lineIndex":"0","imageryIndex":"0"}],"神色":[{"part":"n","lineNum":"11","lineIndex":"3","imageryIndex":"0"}],"水土":[{"part":"n","lineNum":"11","lineIndex":"6","imageryIndex":"1"}],"声":[{"part":"n","lineNum":"13","lineIndex":"3","imageryIndex":"0"}],"浴身":[{"part":"n","lineNum":"14","lineIndex":"5","imageryIndex":"0"}],"内室":[{"part":"n","lineNum":"14","lineIndex":"8","imageryIndex":"1"}],"手指":[{"part":"n","lineNum":"15","lineIndex":"0","imageryIndex":"0"}],"烟":[{"part":"n","lineNum":"15","lineIndex":"5","imageryIndex":"1"}],"皮肤":[{"part":"n","lineNum":"16","lineIndex":"0","imageryIndex":"0"}],"化入":[{"part":"n","lineNum":"16","lineIndex":"2","imageryIndex":"1"}],"空气":[{"part":"n","lineNum":"16","lineIndex":"7","imageryIndex":"2"}],"无人":[{"part":"n","lineNum":"18","lineIndex":"0","imageryIndex":"0"}],"镜子":[{"part":"n","lineNum":"19","lineIndex":"1","imageryIndex":"0"}],"风":[{"part":"n","lineNum":"19","lineIndex":"5","imageryIndex":"1"}],"落草":[{"part":"n","lineNum":"21","lineIndex":"0","imageryIndex":"0"}]}}
