{"title":"要想知道梨子的味道","date":"","imageries":{"梨子":[{"part":"n","lineNum":"1","lineIndex":"4","imageryIndex":"0"},{"part":"n","lineNum":"18","lineIndex":"5","imageryIndex":"0"}],"味道":[{"part":"n","lineNum":"1","lineIndex":"7","imageryIndex":"1"}],"梨树":[{"part":"n","lineNum":"2","lineIndex":"7","imageryIndex":"0"}],"梨":[{"part":"n","lineNum":"3","lineIndex":"8","imageryIndex":"0"},{"part":"n","lineNum":"13","lineIndex":"9","imageryIndex":"1"}],"生":[{"part":"n","lineNum":"4","lineIndex":"8","imageryIndex":"0"}],"父母":[{"part":"n","lineNum":"6","lineIndex":"0","imageryIndex":"0"}],"远游":[{"part":"n","lineNum":"6","lineIndex":"4","imageryIndex":"1"}],"经商":[{"part":"n","lineNum":"6","lineIndex":"7","imageryIndex":"2"}],"做官":[{"part":"n","lineNum":"7","lineIndex":"7","imageryIndex":"0"}],"官":[{"part":"n","lineNum":"8","lineIndex":"5","imageryIndex":"0"}],"寺院":[{"part":"n","lineNum":"8","lineIndex":"8","imageryIndex":"1"}],"看守所":[{"part":"n","lineNum":"9","lineIndex":"2","imageryIndex":"0"}],"女色":[{"part":"n","lineNum":"9","lineIndex":"7","imageryIndex":"1"}],"水果":[{"part":"n","lineNum":"10","lineIndex":"3","imageryIndex":"0"}],"小贩":[{"part":"n","lineNum":"10","lineIndex":"6","imageryIndex":"1"}],"世界":[{"part":"n","lineNum":"11","lineIndex":"7","imageryIndex":"0"}],"上帝":[{"part":"n","lineNum":"13","lineIndex":"4","imageryIndex":"0"}],"核":[{"part":"n","lineNum":"13","lineIndex":"10","imageryIndex":"2"}],"象":[{"part":"n","lineNum":"15","lineIndex":"0","imageryIndex":"0"}],"泥土":[{"part":"n","lineNum":"15","lineIndex":"3","imageryIndex":"1"}],"滋味":[{"part":"n","lineNum":"18","lineIndex":"8","imageryIndex":"1"}],"舌苔":[{"part":"n","lineNum":"19","lineIndex":"1","imageryIndex":"0"}]}}
